constgen/LICENSE
constgen/__init__.py
constgen/config.py
constgen/constgen.py
constgen/example.yaml
constgen/generators/__init__.py
constgen/generators/c/__init__.py
constgen/generators/c/c_generators.py
constgen/generators/common.py
constgen/generators/go/__init__.py
constgen/generators/go/go_generators.py
constgen/generators/java/__init__.py
constgen/generators/java/java_generators.py
constgen/generators/javascript/__init__.py
constgen/generators/javascript/javascript_generators.py
constgen/generators/python/__init__.py
constgen/generators/python/python_generators.py
constgen/generators/rust/__init__.py
constgen/generators/rust/rust_generators.py
constgen/generators/vue/__init__.py
constgen/generators/vue/vue_generators.py
constgen-0.5.1.dist-info/METADATA
constgen-0.5.1.dist-info/WHEEL
constgen-0.5.1.dist-info/entry_points.txt
constgen-0.5.1.dist-info/RECORD
